{"_ts":[1554244075],"_r":{"breakdown":{"html":{"bytes":[90071],"requests":[13]},"js":{"bytes":[758061],"requests":[20]},"css":{"bytes":[69252],"requests":[5]},"image":{"bytes":[90960],"requests":[35]},"flash":{"bytes":[0],"requests":[0]},"font":{"bytes":[135036],"requests":[6]},"video":{"bytes":[0],"requests":[0]},"other":{"bytes":[1562],"requests":[13]}},"date":[1554244075],"domElements":[662],"domInteractive":[981.3333333333334],"firstPaint":[947.6833333334667],"fullyLoaded":[3760.6666666666665],"id":["190402_V1_86d9922bcdf169f6d797938678833353"],"loadTime":[1820],"render":[966.6666666666666],"SpeedIndex":[992.3333333333334],"TTFB":[474.6666666666667],"videoFrames":[[{"_i":"ms_000000.jpg","_t":0,"_vc":0},{"_i":"ms_001100.jpg","_t":1100,"_vc":86},{"_i":"ms_001200.jpg","_t":1200,"_vc":86},{"_i":"ms_001400.jpg","_t":1400,"_vc":100}]],"visualComplete":[1166.6666666666667],"lighthouse":[73],"pagespeed":[81]}}