{"_ts":[1533317555],"_r":{"breakdown":{"html":{"bytes":[94911],"requests":[11]},"js":{"bytes":[1361559],"requests":[25]},"css":{"bytes":[181401],"requests":[2]},"image":{"bytes":[726537],"requests":[44]},"flash":{"bytes":[0],"requests":[0]},"font":{"bytes":[137068],"requests":[6]},"video":{"bytes":[0],"requests":[0]},"other":{"bytes":[64760],"requests":[34]}},"date":[1533317555],"domElements":[1278],"domInteractive":[1128.3333333333],"firstPaint":[1103.1666666652],"fullyLoaded":[10600.666666667],"id":["180803_GH_102bd8aa0519443eda776ef5215c141d"],"loadTime":[2484.3333333333],"render":[1066.6666666667],"SpeedIndex":[1251],"TTFB":[538],"videoFrames":[[{"_i":"ms_000000.jpg","_t":0,"_vc":0},{"_i":"ms_001100.jpg","_t":1100,"_vc":21},{"_i":"ms_001300.jpg","_t":1300,"_vc":100},{"_i":"ms_001400.jpg","_t":1400,"_vc":100}]],"visualComplete":[1300],"lighthouse":[35],"pagespeed":[61]}}