{"_ts":[1525447933],"_r":{"breakdown":{"html":{"bytes":[50825],"requests":[11]},"js":{"bytes":[1441149],"requests":[34]},"css":{"bytes":[216596],"requests":[2]},"image":{"bytes":[152486],"requests":[51]},"flash":{"bytes":[0],"requests":[0]},"font":{"bytes":[0],"requests":[0]},"video":{"bytes":[0],"requests":[0]},"other":{"bytes":[81564],"requests":[38]}},"date":[1525447933],"domElements":[470.33333333333],"domInteractive":[857],"firstPaint":[895.89999999953],"fullyLoaded":[10001],"id":["180504_AJ_5f1848342c836fda423668870296bd64"],"loadTime":[2223],"render":[1166.6666666667],"SpeedIndex":[1194],"TTFB":[347.33333333333],"videoFrames":[[{"_i":"ms_000000.jpg","_t":0,"_vc":0},{"_i":"ms_001200.jpg","_t":1200,"_vc":100}]],"visualComplete":[1200],"lighthouse":[63],"pagespeed":[82]}}