{"_ts":[1567904576],"_r":{"breakdown":{"html":{"bytes":[53302],"requests":[14]},"js":{"bytes":[866031],"requests":[22]},"css":{"bytes":[85629],"requests":[6]},"image":{"bytes":[15691],"requests":[32]},"flash":{"bytes":[0],"requests":[0]},"font":{"bytes":[134760],"requests":[6]},"video":{"bytes":[0],"requests":[0]},"other":{"bytes":[1546],"requests":[12]}},"date":[1567904576],"domElements":[606],"domInteractive":[860.6666666666666],"firstPaint":[820.3049999986666],"fullyLoaded":[3138.6666666666665],"id":["190908_TD_411cb2840c26ceaac0ee958df640e965"],"loadTime":[1866.6666666666667],"render":[866.6666666666666],"SpeedIndex":[888.3333333333334],"TTFB":[441.3333333333333],"videoFrames":[[{"_i":"ms_000000.jpg","_t":0,"_vc":0},{"_i":"ms_000700.jpg","_t":700,"_vc":94},{"_i":"ms_001100.jpg","_t":1100,"_vc":100}]],"visualComplete":[1233.3333333333333],"lighthouse":[73],"pagespeed":[79]}}