{"_ts":[1572568537],"_r":{"breakdown":{"html":{"bytes":[93940],"requests":[13]},"js":{"bytes":[2939618],"requests":[39]},"css":{"bytes":[278911],"requests":[6]},"image":{"bytes":[531258],"requests":[63]},"flash":{"bytes":[0],"requests":[0]},"font":{"bytes":[140892],"requests":[7]},"video":{"bytes":[0],"requests":[0]},"other":{"bytes":[22786],"requests":[35]}},"date":[1572568537],"domElements":[1254.6666666666667],"domInteractive":[1156.3333333333333],"firstPaint":[1621.256666666667],"fullyLoaded":[5831.666666666667],"id":["191101_C3_c46225a0b1aeaca3da5a1c23e22df036"],"loadTime":[3382.6666666666665],"render":[1633.3333333333333],"SpeedIndex":[1724.3333333333333],"TTFB":[608],"videoFrames":[[{"_i":"ms_000000.jpg","_t":0,"_vc":0},{"_i":"ms_001200.jpg","_t":1200,"_vc":85},{"_i":"ms_001600.jpg","_t":1600,"_vc":90},{"_i":"ms_001900.jpg","_t":1900,"_vc":90},{"_i":"ms_002100.jpg","_t":2100,"_vc":89},{"_i":"ms_002900.jpg","_t":2900,"_vc":100}]],"visualComplete":[3033.3333333333335],"lighthouse":[73],"pagespeed":[75]}}