{"_ts":[1512158249,1512763192,1513368266,1513985995],"_r":{"breakdown":{"html":{"bytes":[64040,64184,67384,71730],"requests":[11,11,9,9]},"js":{"bytes":[834481,835568,990558,1063619],"requests":[18,19,19,17]},"css":{"bytes":[170130,170130,246460,233454],"requests":[2,2,2,2]},"image":{"bytes":[503081,499163,1109579,1284452],"requests":[50,50,42,45]},"flash":{"bytes":[0,0,0,0],"requests":[0,0,0,0]},"font":{"bytes":[76924,76924,117160,117160],"requests":[4,4,3,3]},"video":{"bytes":[0,0,0,0],"requests":[0,0,0,0]},"other":{"bytes":[22302,22336,45446,47292],"requests":[32,32,32,33]}},"date":[1512158249,1512763192,1513368266,1513985995],"domElements":[999,1000,816,818],"domInteractive":[985.33333333333,1188,1213.3333333333,978.66666666667],"firstPaint":[984.33333333333,1190,1268.3333333333,1084],"fullyLoaded":[9300.3333333333,9044,9237,9858.3333333333],"id":["171201_ZJ_f5fc104f01eb05822b9d903b6d8668b9","171208_MQ_72d69d3a54d0fdf04b14ab0618251f60","171215_X2_641f5bfb40b976430ba44bcae0dfb7bc","171222_WQ_9b956831508a582f8ecd589e560d8663"],"loadTime":[2803.6666666667,2834,2096.6666666667,2819],"render":[988.66666666667,1200.3333333333,1266.6666666667,1133.6666666667],"SpeedIndex":[1226.3333333333,1461.3333333333,1418,1259],"TTFB":[225.33333333333,402,412.66666666667,246.33333333333],"videoFrames":[[{"_i":"ms_000000.jpg","_t":0,"_vc":0},{"_i":"ms_001067.jpg","_t":1067,"_vc":62},{"_i":"ms_001200.jpg","_t":1200,"_vc":62},{"_i":"ms_001300.jpg","_t":1300,"_vc":62},{"_i":"ms_001433.jpg","_t":1433,"_vc":62},{"_i":"ms_001567.jpg","_t":1567,"_vc":99},{"_i":"ms_001800.jpg","_t":1800,"_vc":99},{"_i":"ms_002067.jpg","_t":2067,"_vc":99},{"_i":"ms_002100.jpg","_t":2100,"_vc":99},{"_i":"ms_002167.jpg","_t":2167,"_vc":99},{"_i":"ms_002233.jpg","_t":2233,"_vc":99},{"_i":"ms_002300.jpg","_t":2300,"_vc":99},{"_i":"ms_002333.jpg","_t":2333,"_vc":99},{"_i":"ms_002367.jpg","_t":2367,"_vc":99},{"_i":"ms_002400.jpg","_t":2400,"_vc":99},{"_i":"ms_002433.jpg","_t":2433,"_vc":99},{"_i":"ms_002467.jpg","_t":2467,"_vc":99},{"_i":"ms_002500.jpg","_t":2500,"_vc":99},{"_i":"ms_002567.jpg","_t":2567,"_vc":99},{"_i":"ms_002633.jpg","_t":2633,"_vc":99},{"_i":"ms_002800.jpg","_t":2800,"_vc":99},{"_i":"ms_003233.jpg","_t":3233,"_vc":99},{"_i":"ms_003267.jpg","_t":3267,"_vc":99},{"_i":"ms_003333.jpg","_t":3333,"_vc":99},{"_i":"ms_003367.jpg","_t":3367,"_vc":99},{"_i":"ms_003400.jpg","_t":3400,"_vc":100},{"_i":"ms_004367.jpg","_t":4367,"_vc":99},{"_i":"ms_004767.jpg","_t":4767,"_vc":99},{"_i":"ms_004800.jpg","_t":4800,"_vc":99},{"_i":"ms_004867.jpg","_t":4867,"_vc":99},{"_i":"ms_004900.jpg","_t":4900,"_vc":99},{"_i":"ms_004933.jpg","_t":4933,"_vc":100}],[{"_i":"ms_000000.jpg","_t":0,"_vc":0},{"_i":"ms_001267.jpg","_t":1267,"_vc":55},{"_i":"ms_001300.jpg","_t":1300,"_vc":55},{"_i":"ms_001333.jpg","_t":1333,"_vc":55},{"_i":"ms_001367.jpg","_t":1367,"_vc":55},{"_i":"ms_001400.jpg","_t":1400,"_vc":55},{"_i":"ms_001433.jpg","_t":1433,"_vc":55},{"_i":"ms_001467.jpg","_t":1467,"_vc":55},{"_i":"ms_001500.jpg","_t":1500,"_vc":55},{"_i":"ms_001533.jpg","_t":1533,"_vc":55},{"_i":"ms_001567.jpg","_t":1567,"_vc":55},{"_i":"ms_001633.jpg","_t":1633,"_vc":55},{"_i":"ms_001667.jpg","_t":1667,"_vc":55},{"_i":"ms_001700.jpg","_t":1700,"_vc":55},{"_i":"ms_001800.jpg","_t":1800,"_vc":100},{"_i":"ms_001867.jpg","_t":1867,"_vc":99},{"_i":"ms_002033.jpg","_t":2033,"_vc":100},{"_i":"ms_002133.jpg","_t":2133,"_vc":100},{"_i":"ms_002233.jpg","_t":2233,"_vc":99},{"_i":"ms_002367.jpg","_t":2367,"_vc":99},{"_i":"ms_002433.jpg","_t":2433,"_vc":99},{"_i":"ms_002500.jpg","_t":2500,"_vc":99},{"_i":"ms_002533.jpg","_t":2533,"_vc":99},{"_i":"ms_002567.jpg","_t":2567,"_vc":99},{"_i":"ms_002600.jpg","_t":2600,"_vc":99},{"_i":"ms_002667.jpg","_t":2667,"_vc":99},{"_i":"ms_002700.jpg","_t":2700,"_vc":99},{"_i":"ms_002733.jpg","_t":2733,"_vc":99},{"_i":"ms_002800.jpg","_t":2800,"_vc":100}],[{"_i":"ms_000000.jpg","_t":0,"_vc":0},{"_i":"ms_001100.jpg","_t":1100,"_vc":55},{"_i":"ms_001167.jpg","_t":1167,"_vc":55},{"_i":"ms_001233.jpg","_t":1233,"_vc":55},{"_i":"ms_001267.jpg","_t":1267,"_vc":55},{"_i":"ms_001300.jpg","_t":1300,"_vc":55},{"_i":"ms_001333.jpg","_t":1333,"_vc":55},{"_i":"ms_001367.jpg","_t":1367,"_vc":55},{"_i":"ms_001400.jpg","_t":1400,"_vc":54},{"_i":"ms_001433.jpg","_t":1433,"_vc":99},{"_i":"ms_001500.jpg","_t":1500,"_vc":99},{"_i":"ms_001567.jpg","_t":1567,"_vc":100},{"_i":"ms_001700.jpg","_t":1700,"_vc":100},{"_i":"ms_001900.jpg","_t":1900,"_vc":100},{"_i":"ms_001967.jpg","_t":1967,"_vc":100},{"_i":"ms_002033.jpg","_t":2033,"_vc":100},{"_i":"ms_002100.jpg","_t":2100,"_vc":100},{"_i":"ms_002133.jpg","_t":2133,"_vc":100},{"_i":"ms_002167.jpg","_t":2167,"_vc":100},{"_i":"ms_002200.jpg","_t":2200,"_vc":100},{"_i":"ms_002267.jpg","_t":2267,"_vc":100},{"_i":"ms_002300.jpg","_t":2300,"_vc":100},{"_i":"ms_002333.jpg","_t":2333,"_vc":100},{"_i":"ms_002367.jpg","_t":2367,"_vc":100},{"_i":"ms_002400.jpg","_t":2400,"_vc":100},{"_i":"ms_002433.jpg","_t":2433,"_vc":100},{"_i":"ms_002467.jpg","_t":2467,"_vc":100},{"_i":"ms_002500.jpg","_t":2500,"_vc":100},{"_i":"ms_002533.jpg","_t":2533,"_vc":100},{"_i":"ms_002567.jpg","_t":2567,"_vc":100},{"_i":"ms_002600.jpg","_t":2600,"_vc":100},{"_i":"ms_002667.jpg","_t":2667,"_vc":99},{"_i":"ms_002833.jpg","_t":2833,"_vc":100}],[{"_i":"ms_000000.jpg","_t":0,"_vc":0},{"_i":"ms_001367.jpg","_t":1367,"_vc":61},{"_i":"ms_001433.jpg","_t":1433,"_vc":61},{"_i":"ms_001467.jpg","_t":1467,"_vc":61},{"_i":"ms_001500.jpg","_t":1500,"_vc":61},{"_i":"ms_001533.jpg","_t":1533,"_vc":61},{"_i":"ms_001567.jpg","_t":1567,"_vc":61},{"_i":"ms_001600.jpg","_t":1600,"_vc":61},{"_i":"ms_001633.jpg","_t":1633,"_vc":61},{"_i":"ms_001667.jpg","_t":1667,"_vc":99},{"_i":"ms_001700.jpg","_t":1700,"_vc":99},{"_i":"ms_001733.jpg","_t":1733,"_vc":99},{"_i":"ms_001767.jpg","_t":1767,"_vc":99},{"_i":"ms_001800.jpg","_t":1800,"_vc":99},{"_i":"ms_001833.jpg","_t":1833,"_vc":99},{"_i":"ms_001867.jpg","_t":1867,"_vc":99},{"_i":"ms_001900.jpg","_t":1900,"_vc":99},{"_i":"ms_002167.jpg","_t":2167,"_vc":99},{"_i":"ms_002200.jpg","_t":2200,"_vc":99},{"_i":"ms_002233.jpg","_t":2233,"_vc":99},{"_i":"ms_002267.jpg","_t":2267,"_vc":99},{"_i":"ms_002300.jpg","_t":2300,"_vc":99},{"_i":"ms_002333.jpg","_t":2333,"_vc":99},{"_i":"ms_002367.jpg","_t":2367,"_vc":99},{"_i":"ms_002400.jpg","_t":2400,"_vc":99},{"_i":"ms_002433.jpg","_t":2433,"_vc":99},{"_i":"ms_002467.jpg","_t":2467,"_vc":99},{"_i":"ms_002500.jpg","_t":2500,"_vc":99},{"_i":"ms_002533.jpg","_t":2533,"_vc":99},{"_i":"ms_002567.jpg","_t":2567,"_vc":99},{"_i":"ms_002600.jpg","_t":2600,"_vc":99},{"_i":"ms_002633.jpg","_t":2633,"_vc":99},{"_i":"ms_002667.jpg","_t":2667,"_vc":99},{"_i":"ms_002700.jpg","_t":2700,"_vc":99},{"_i":"ms_002733.jpg","_t":2733,"_vc":99},{"_i":"ms_002767.jpg","_t":2767,"_vc":99},{"_i":"ms_002800.jpg","_t":2800,"_vc":99},{"_i":"ms_002867.jpg","_t":2867,"_vc":99},{"_i":"ms_002900.jpg","_t":2900,"_vc":99},{"_i":"ms_002933.jpg","_t":2933,"_vc":100},{"_i":"ms_004400.jpg","_t":4400,"_vc":99},{"_i":"ms_004767.jpg","_t":4767,"_vc":99},{"_i":"ms_004800.jpg","_t":4800,"_vc":99},{"_i":"ms_004833.jpg","_t":4833,"_vc":99},{"_i":"ms_004900.jpg","_t":4900,"_vc":99},{"_i":"ms_004933.jpg","_t":4933,"_vc":100}]],"visualComplete":[2322,2189,1855.6666666667,2989],"lighthouse":[63,63,63,63],"pagespeed":[78,78,77,75]}}