{"_ts":[1527869001],"_r":{"breakdown":{"html":{"bytes":[56956],"requests":[10]},"js":{"bytes":[1426770],"requests":[31]},"css":{"bytes":[185643],"requests":[2]},"image":{"bytes":[85014],"requests":[41]},"flash":{"bytes":[0],"requests":[0]},"font":{"bytes":[0],"requests":[0]},"video":{"bytes":[0],"requests":[0]},"other":{"bytes":[78137],"requests":[39]}},"date":[1527869001],"domElements":[463],"domInteractive":[928],"firstPaint":[972.79999999987],"fullyLoaded":[10744.666666667],"id":["180601_AW_7380d80acd933739107083a4b213aa41"],"loadTime":[2303],"render":[1166.6666666667],"SpeedIndex":[1169],"TTFB":[398],"videoFrames":[[{"_i":"ms_000000.jpg","_t":0,"_vc":0},{"_i":"ms_001300.jpg","_t":1300,"_vc":100}]],"visualComplete":[1266.6666666667],"lighthouse":[63],"pagespeed":[84]}}