{"_ts":[1517617932,1518223717],"_r":{"breakdown":{"html":{"bytes":[91094,78935],"requests":[1,1]},"js":{"bytes":[760157,685168],"requests":[9,9]},"css":{"bytes":[1888,1888],"requests":[1,1]},"image":{"bytes":[1203998,1203998],"requests":[44,44]},"flash":{"bytes":[0,0],"requests":[0,0]},"font":{"bytes":[156528,156528],"requests":[4,4]},"video":{"bytes":[0,0],"requests":[0,0]},"other":{"bytes":[15294,15302],"requests":[15,15]}},"date":[1517617932,1518223717],"domElements":[929,930],"domInteractive":[747.33333333333,1069.3333333333],"firstPaint":[750.53333332957,1074.7666666672],"fullyLoaded":[2814.6666666667,3057.3333333333],"id":["180203_SA_e414c6e358a1c221665e3a98ddbedcc9","180210_WW_3c4b7b2fe6c281fc5e8e57fafdcadd55"],"loadTime":[1518,1690],"render":[744.66666666667,1078],"SpeedIndex":[827.66666666667,1148],"TTFB":[347,635.33333333333],"videoFrames":[[{"_i":"ms_000000.jpg","_t":0,"_vc":0},{"_i":"ms_000734.jpg","_t":734,"_vc":65},{"_i":"ms_000900.jpg","_t":900,"_vc":86},{"_i":"ms_000967.jpg","_t":967,"_vc":99},{"_i":"ms_001334.jpg","_t":1334,"_vc":99},{"_i":"ms_001400.jpg","_t":1400,"_vc":99},{"_i":"ms_001467.jpg","_t":1467,"_vc":99},{"_i":"ms_001500.jpg","_t":1500,"_vc":100},{"_i":"ms_001734.jpg","_t":1734,"_vc":100},{"_i":"ms_001767.jpg","_t":1767,"_vc":100}],[{"_i":"ms_000000.jpg","_t":0,"_vc":0},{"_i":"ms_001667.jpg","_t":1667,"_vc":65},{"_i":"ms_001700.jpg","_t":1700,"_vc":65},{"_i":"ms_001733.jpg","_t":1733,"_vc":65},{"_i":"ms_001767.jpg","_t":1767,"_vc":65},{"_i":"ms_001800.jpg","_t":1800,"_vc":86},{"_i":"ms_001833.jpg","_t":1833,"_vc":86},{"_i":"ms_001867.jpg","_t":1867,"_vc":100},{"_i":"ms_001967.jpg","_t":1967,"_vc":99},{"_i":"ms_002400.jpg","_t":2400,"_vc":99},{"_i":"ms_002467.jpg","_t":2467,"_vc":99},{"_i":"ms_002500.jpg","_t":2500,"_vc":99},{"_i":"ms_002600.jpg","_t":2600,"_vc":100}]],"visualComplete":[1955.6666666667,1955.6666666667],"lighthouse":[63,null],"pagespeed":[65,65]}}