{"_ts":[1557272948],"_r":{"breakdown":{"html":{"bytes":[71852],"requests":[13]},"js":{"bytes":[1836832],"requests":[41]},"css":{"bytes":[191730],"requests":[4]},"image":{"bytes":[10652],"requests":[54]},"flash":{"bytes":[0],"requests":[0]},"font":{"bytes":[118384],"requests":[6]},"video":{"bytes":[0],"requests":[0]},"other":{"bytes":[3837],"requests":[25]}},"date":[1557272948],"domElements":[474],"domInteractive":[752.3333333333334],"firstPaint":[1406.7149999997666],"fullyLoaded":[4189.666666666667],"id":["190507_K1_ec153cafdbe2577891e199c63dc8d60e"],"loadTime":[2600.3333333333335],"render":[1466.6666666666667],"SpeedIndex":[1487],"TTFB":[460],"videoFrames":[[{"_i":"ms_000000.jpg","_t":0,"_vc":0},{"_i":"ms_002100.jpg","_t":2100,"_vc":96},{"_i":"ms_002300.jpg","_t":2300,"_vc":99},{"_i":"ms_003000.jpg","_t":3000,"_vc":100}]],"visualComplete":[2433.3333333333335],"lighthouse":[65],"pagespeed":[78]}}