{"_ts":[1486713358,1487926633,1488095991],"_r":{"breakdown":{"html":{"bytes":[94268,67326,70222],"requests":[15,2,7]},"js":{"bytes":[1068988,915057,938010],"requests":[17,9,13]},"css":{"bytes":[128926,137832,139533],"requests":[3,2,4]},"image":{"bytes":[55213,46966,46975],"requests":[30,6,6]},"flash":{"bytes":[0,0,0],"requests":[0,0,0]},"font":{"bytes":[79704,61322,79704],"requests":[4,3,4]},"other":{"bytes":[81018,5592,74053],"requests":[32,6,27]}},"date":[1486713358,1487926633,1488095991],"domElements":[753,994,701.33333333333],"domInteractive":[1683,1541,1804.3333333333],"firstPaint":[1479,2434,2690.6666666667],"fullyLoaded":[10939,3143,8869],"id":["170210_F0_DH7","170224_FG_DBT","170226_NK_1KWJ"],"loadTime":[5816,2717,3560],"render":[1681,2581,2883.3333333333],"SpeedIndex":[2297,2581,3072],"TTFB":[187,196,198],"videoFrames":[[{"_t":0,"_vc":0},{"_t":1700,"_vc":92},{"_t":3200,"_vc":94},{"_t":3300,"_vc":94},{"_t":5600,"_vc":94},{"_t":5700,"_vc":94},{"_t":5900,"_vc":93},{"_t":6100,"_vc":93},{"_t":6200,"_vc":93},{"_t":6400,"_vc":93},{"_t":6500,"_vc":93},{"_t":6700,"_vc":92},{"_t":6900,"_vc":92},{"_t":7200,"_vc":92},{"_t":7400,"_vc":92},{"_t":10700,"_vc":92},{"_t":10800,"_vc":100},{"_t":11100,"_vc":99},{"_t":11700,"_vc":100},{"_t":12200,"_vc":99},{"_t":12700,"_vc":100}],[{"_t":0,"_vc":0},{"_t":2600,"_vc":100}],[{"_t":0,"_vc":0},{"_t":2500,"_vc":93},{"_t":2700,"_vc":94},{"_t":3300,"_vc":95},{"_t":5800,"_vc":95},{"_t":5900,"_vc":95},{"_t":6100,"_vc":94},{"_t":6200,"_vc":94},{"_t":6400,"_vc":94},{"_t":6500,"_vc":94},{"_t":6700,"_vc":94},{"_t":6800,"_vc":94},{"_t":6900,"_vc":93},{"_t":7100,"_vc":93},{"_t":7300,"_vc":93},{"_t":7500,"_vc":93},{"_t":8200,"_vc":93},{"_t":8300,"_vc":93},{"_t":8400,"_vc":100},{"_t":8600,"_vc":100},{"_t":9100,"_vc":100},{"_t":9700,"_vc":100},{"_t":10200,"_vc":100},{"_t":10800,"_vc":100},{"_t":11200,"_vc":100},{"_t":11700,"_vc":100},{"_t":12300,"_vc":100},{"_t":12800,"_vc":100},{"_t":13300,"_vc":100}]],"visualComplete":[10781,2581,7494.3333333333]}}