{"_ts":[1494581343],"_r":{"breakdown":{"html":{"bytes":[64108],"requests":[4]},"js":{"bytes":[1425373],"requests":[25]},"css":{"bytes":[186172],"requests":[5]},"image":{"bytes":[461583],"requests":[11]},"flash":{"bytes":[0],"requests":[0]},"font":{"bytes":[79704],"requests":[4]},"other":{"bytes":[66767],"requests":[29]}},"date":[1494581343],"domElements":[779],"domInteractive":[2918],"firstPaint":[3442.6666666667],"fullyLoaded":[12705.666666667],"id":["170512_GQ_HMS"],"loadTime":[7582.6666666667],"render":[3581.3333333333],"SpeedIndex":[3884],"TTFB":[525.33333333333],"videoFrames":[[{"_i":"frame_0000.jpg","_t":0,"_vc":0},{"_i":"frame_0037.jpg","_t":3700,"_vc":81},{"_i":"frame_0053.jpg","_t":5300,"_vc":99},{"_i":"frame_0077.jpg","_t":7700,"_vc":99},{"_i":"frame_0079.jpg","_t":7900,"_vc":100},{"_i":"frame_0098.jpg","_t":9800,"_vc":99},{"_i":"frame_0099.jpg","_t":9900,"_vc":99},{"_i":"frame_0101.jpg","_t":10100,"_vc":99},{"_i":"frame_0106.jpg","_t":10600,"_vc":99},{"_i":"frame_0107.jpg","_t":10700,"_vc":99},{"_i":"frame_0109.jpg","_t":10900,"_vc":99},{"_i":"frame_0111.jpg","_t":11100,"_vc":100}]],"visualComplete":[7233.3333333333],"lighthouse":[null],"pagespeed":[83]}}